odoo/addons/product_harmonized_system_delivery/README.rst
odoo/addons/product_harmonized_system_delivery/__init__.py
odoo/addons/product_harmonized_system_delivery/__manifest__.py
odoo/addons/product_harmonized_system_delivery/i18n/product_harmonized_system_delivery.pot
odoo/addons/product_harmonized_system_delivery/readme/CONTRIBUTORS.rst
odoo/addons/product_harmonized_system_delivery/readme/DESCRIPTION.rst
odoo/addons/product_harmonized_system_delivery/static/description/icon.png
odoo/addons/product_harmonized_system_delivery/static/description/index.html
odoo/addons/product_harmonized_system_delivery/views/product_template.xml
odoo11_addon_product_harmonized_system_delivery-11.0.1.0.0.99.dev6.dist-info/METADATA
odoo11_addon_product_harmonized_system_delivery-11.0.1.0.0.99.dev6.dist-info/WHEEL
odoo11_addon_product_harmonized_system_delivery-11.0.1.0.0.99.dev6.dist-info/top_level.txt
odoo11_addon_product_harmonized_system_delivery-11.0.1.0.0.99.dev6.dist-info/RECORD
